Alu.v
module alu_16_bit(
    input [15:0]A,
    input [15:0]B,
    input [2:0]sel,
    output reg [15:0] Y
);

always @(*)begin
    case(sel)
    3'b000: Y = A+B;
    3'b001: Y = A-B;
    3'b010: Y = A & B;
    3'b011: Y = A|B;
    3'b100: Y = A^B;
    3'b101: Y = ~A;
    3'b110: Y = A<<1;
    3'b111: Y = A>>1;
    endcase
end
endmodule

Alu_tb.v
module tb_alu;

reg [15:0] a,b;
reg [2:0] sel;
wire [15:0] result;

// instantiate ALU

alu_16_bit uut (
    .A(a),
    .B(b),
    .sel(sel),
    .Y(result)
);

initial begin
    $dumpfile("dump.vcd");
    $dumpvars(0,tb_alu);
    $monitor("A = %d B = %d sel = %b result = %d",a,b,sel,result);
    a = 10; b = 5;

    sel = 3'b000; #10;
    sel = 3'b001; #10;
    sel = 3'b010; #10;
    sel = 3'b011; #10;
    sel = 3'b100; #10;
    sel = 3'b101; #10;
    sel = 3'b110; #10;
    sel = 3'b111; #10;
    $finish;
end
endmodule

dump.vcd
$date
	Mon Mar 23 23:12:06 2026
$end
$version
	Icarus Verilog
$end
$timescale
	1s
$end
$scope module tb_alu $end
$var wire 16 ! result [15:0] $end
$var reg 16 " a [15:0] $end
$var reg 16 # b [15:0] $end
$var reg 3 $ sel [2:0] $end
$scope module uut $end
$var wire 16 % A [15:0] $end
$var wire 16 & B [15:0] $end
$var wire 3 ' sel [2:0] $end
$var reg 16 ( Y [15:0] $end
$upscope $end
$upscope $end
$enddefinitions $end
$comment Show the parameter values. $end
$dumpall
$end
#0
$dumpvars
b1111 (
b0 '
b101 &
b1010 %
b0 $
b101 #
b1010 "
b1111 !
$end
#10
b101 !
b101 (
b1 $
b1 '
#20
b0 !
b0 (
b10 $
b10 '
#30
b1111 !
b1111 (
b11 $
b11 '
#40
b100 $
b100 '
#50
b1111111111110101 !
b1111111111110101 (
b101 $
b101 '
#60
b10100 !
b10100 (
b110 $
b110 '
#70
b101 !
b101 (
b111 $
b111 '
